contablidad/__init__.py
contablidad/calcular_balanco.py
contablidad/calcular_rescisao.py
contablidad/exportar_pdf.py
contablidad/grafico.py
contablidad/registrar_transacao.py
Contablidad-0.1.2.dist-info/METADATA
Contablidad-0.1.2.dist-info/WHEEL
Contablidad-0.1.2.dist-info/top_level.txt
Contablidad-0.1.2.dist-info/RECORD
