Metadata-Version: 2.1
Name: Contablidad
Version: 0.1.2
Summary: Biblioteca
Author: crisly
Author-email: crislymaria21@gmail.com
Keywords: python,contablidad
Classifier: Development Status :: 3 - Alpha
Requires-Dist: numpy
Requires-Dist: matplotlib
Requires-Dist: fpdf
